griddify/__init__.py
griddify/cloud.py
griddify/datasets.py
griddify/features.py
griddify/grid.py
griddify/plots.py
griddify/preprocess.py
griddify/rearrange.py
griddify-0.0.2.dist-info/LICENSE
griddify-0.0.2.dist-info/METADATA
griddify-0.0.2.dist-info/WHEEL
griddify-0.0.2.dist-info/top_level.txt
griddify-0.0.2.dist-info/RECORD
