Metadata-Version: 2.1
Name: griddify
Version: 0.0.2
Summary: Griddify high-dimensional tabular data for easy visualization and deep learning
Home-page: https://github.com/ersilia-os/griddify
Author: Miquel Duran-Frigola
Author-email: miquel@ersilia.io
License: MIT
Project-URL: Source Code, https://github.com/ersilia-os/griddify
Keywords: data-visualization
Classifier: Programming Language :: Python :: 3.6
Classifier: Programming Language :: Python :: 3.7
Classifier: License :: OSI Approved :: MIT License
Classifier: Operating System :: OS Independent
Classifier: Topic :: Scientific/Engineering :: Artificial Intelligence
Requires-Python: >=3.6
License-File: LICENSE
Requires-Dist: matplotlib
Requires-Dist: numpy
Requires-Dist: pandas
Requires-Dist: umap-learn
Requires-Dist: scikit-learn
Requires-Dist: lapx
